vecshare/__init__.py
vecshare/indexer.py
vecshare/info.py
vecshare/poll.py
vecshare/signatures.py
vecshare/sim_benchmark.py
vecshare/vecshare.py
vecshare-1.3.9.dist-info/DESCRIPTION.rst
vecshare-1.3.9.dist-info/METADATA
vecshare-1.3.9.dist-info/RECORD
vecshare-1.3.9.dist-info/WHEEL
vecshare-1.3.9.dist-info/metadata.json
vecshare-1.3.9.dist-info/top_level.txt
