Metadata-Version: 2.0
Name: vecshare
Version: 1.3.9
Summary: Python library for sharing word embeddings
Home-page: https://github.com/JaredFern/VecShare
Author: JaredFern
Author-email: jared.fern@u.northwestern.edu
License: Apache 2.0
Keywords: word embeddings,word vectors,vecshare,natural language processing,NLP
Platform: UNKNOWN
Classifier: Development Status :: 5 - Production/Stable
Classifier: Intended Audience :: Developers
Classifier: Intended Audience :: Science/Research
Classifier: Operating System :: OS Independent
Classifier: License :: OSI Approved :: Apache Software License
Classifier: Programming Language :: Python :: 2.7
Classifier: Programming Language :: Python :: 3
Classifier: Programming Language :: Python :: 3.4
Classifier: Programming Language :: Python :: 3.5
Classifier: Programming Language :: Python :: 3.6
Classifier: Topic :: Software Development :: Libraries :: Python Modules
Classifier: Topic :: Scientific/Engineering :: Information Analysis
Requires-Dist: pandas
Requires-Dist: numpy
Requires-Dist: nltk
Requires-Dist: scipy
Requires-Dist: datadotworld
Requires-Dist: bs4
Requires-Dist: selenium
Requires-Dist: progressbar2
Requires-Dist: tabulate
Requires-Dist: pytz
Requires-Dist: pyvirtualdisplay
Requires-Dist: sklearn
Requires-Dist: pathos
Requires-Dist: requests
Requires-Dist: unicodecsv
